yt_videos_list/__init__.py
yt_videos_list/__main__.py
yt_videos_list/custom_logger.py
yt_videos_list/logic.py
yt_videos_list/notifications.py
yt_videos_list/program.py
yt_videos_list/script.py
yt_videos_list/scroller.py
yt_videos_list/writer.py
yt_videos_list/download/__init__.py
yt_videos_list/download/selenium_linux.py
yt_videos_list/download/selenium_macos.py
yt_videos_list/download/selenium_webdriver_dependencies.py
yt_videos_list/download/selenium_windows.py
yt_videos_list/download/user_os_info.py
yt_videos_list/download/windows_info.py
yt_videos_list-0.6.7.dist-info/METADATA
yt_videos_list-0.6.7.dist-info/WHEEL
yt_videos_list-0.6.7.dist-info/top_level.txt
yt_videos_list-0.6.7.dist-info/RECORD
