Metadata-Version: 2.1
Name: yt-videos-list
Version: 0.6.7
Summary: YouTube bot to make a YouTube videos list (including all video titles and URLs uploaded by a channel) with end-to-end web scraping - no API tokens required. 🌟 Star this repo if you found it useful! 🌟
Home-page: https://github.com/slow-but-steady/yt-videos-list/tree/main/python
Author: slow-but-steady
Author-email: yt.videos.list@gmail.com
License: Apache License 2.0
Project-URL: Bug Reports, https://github.com/slow-but-steady/yt-videos-list/issues
Project-URL: PyPi Funding, https://donate.pypi.org
Project-URL: Source, https://github.com/slow-but-steady/yt-videos-list/tree/main/python
Keywords: YouTube videos URL scraping automation Selenium csv txt macos windows linux
Platform: UNKNOWN
Classifier: Development Status :: 4 - Beta
Classifier: Intended Audience :: Developers
Classifier: License :: Free for non-commercial use
Classifier: License :: OSI Approved :: Apache Software License
Classifier: Natural Language :: English
Classifier: Operating System :: MacOS :: MacOS X
Classifier: Operating System :: Microsoft :: Windows :: Windows 10
Classifier: Programming Language :: Python :: 3.6
Classifier: Programming Language :: Python :: 3.7
Classifier: Programming Language :: Python :: 3.8
Classifier: Programming Language :: Python :: 3.9
Classifier: Programming Language :: Python :: 3 :: Only
Classifier: Topic :: Database :: Front-Ends
Classifier: Topic :: Home Automation
Classifier: Topic :: Internet :: WWW/HTTP :: Dynamic Content
Classifier: Topic :: Internet :: WWW/HTTP :: Dynamic Content :: CGI Tools/Libraries
Classifier: Topic :: Internet :: WWW/HTTP :: Indexing/Search
Classifier: Topic :: Multimedia :: Video
Classifier: Topic :: Scientific/Engineering :: Information Analysis
Classifier: Topic :: Software Development :: Libraries :: Python Modules
Classifier: Topic :: Software Development :: Version Control :: Git
Classifier: Topic :: Text Processing :: Markup :: HTML
Requires-Python: >=3.6, <4
Requires-Dist: urllib3 (<=1.26.18,>=1.26.0)
Requires-Dist: selenium (<4,>=3.141.0)
Requires-Dist: save-thread-result (==0.1.1)
